smControl/SignalControl.py
smControl/__init__.py
smControl-0.0.1.dist-info/LICENSE
smControl-0.0.1.dist-info/METADATA
smControl-0.0.1.dist-info/WHEEL
smControl-0.0.1.dist-info/top_level.txt
smControl-0.0.1.dist-info/RECORD
