Metadata-Version: 2.1
Name: smControl
Version: 0.0.1
Summary: driver for micropython 
Author: Cesar
Author-email: unit@noreply.com
License: MIT License
License-File: LICENSE
